MANIFEST.in
README.rst
bootstrap-buildout.py
buildout.cfg
requirements.txt
setup.py
version.txt
bob/__init__.py
bob.db.pola_thermal.egg-info/PKG-INFO
bob.db.pola_thermal.egg-info/SOURCES.txt
bob.db.pola_thermal.egg-info/dependency_links.txt
bob.db.pola_thermal.egg-info/entry_points.txt
bob.db.pola_thermal.egg-info/namespace_packages.txt
bob.db.pola_thermal.egg-info/not-zip-safe
bob.db.pola_thermal.egg-info/requires.txt
bob.db.pola_thermal.egg-info/top_level.txt
bob/db/__init__.py
bob/db/pola_thermal/__init__.py
bob/db/pola_thermal/create.py
bob/db/pola_thermal/driver.py
bob/db/pola_thermal/models.py
bob/db/pola_thermal/query.py
bob/db/pola_thermal/test.py
bob/db/pola_thermal/utils.py
doc/conf.py
doc/guide.rst
doc/index.rst
doc/py_api.rst
doc/references.rst